pyfolio_performance/__init__.py
pyfolio_performance/classAccount.py
pyfolio_performance/classCrossEntry.py
pyfolio_performance/classDateObject.py
pyfolio_performance/classDepot.py
pyfolio_performance/classFilters.py
pyfolio_performance/classPortfolio.py
pyfolio_performance/classPortfolioPerformanceObject.py
pyfolio_performance/classSecurity.py
pyfolio_performance/classTransaction.py
pyfolio_performance/helpers.py
pyfolio_performance-0.2.5.dist-info/LICENSE
pyfolio_performance-0.2.5.dist-info/METADATA
pyfolio_performance-0.2.5.dist-info/WHEEL
pyfolio_performance-0.2.5.dist-info/top_level.txt
pyfolio_performance-0.2.5.dist-info/RECORD
